{
  "processor": {
    "brands": {
      "amd": {
        "models": {
          "ryzen-3 3100": {
            "price": 150
          },
          "ryzen-3 3300X": {
            "price": 160
          },
          "ryzen-5 3600": {
            "price": 250
          },
          "ryzen-5 5600X": {
            "price": 300
          },
          "ryzen-7 3700X": {
            "price": 350
          },
          "ryzen-7 5800X": {
            "price": 400
          },
          "ryzen-9 3900X": {
            "price": 450
          },
          "ryzen-9 5900X": {
            "price": 550
          }
        }
      },
      "intel": {
        "models": {
          "i3-10100": {
            "price": 180
          },
          "i3-10320": {
            "price": 190
          },
          "i5-10400": {
            "price": 270
          },
          "i5-10600K": {
            "price": 320
          },
          "i7-10700": {
            "price": 370
          },
          "i7-11700K": {
            "price": 420
          },
          "i9-10900K": {
            "price": 470
          },
          "i9-11900K": {
            "price": 520
          }
        }
      }
    }
  },
  "motherboard": {
    "brands": {
      "asus": {
        "models": {
          "ROG Strix B550-F Gaming": {
            "price": 200
          },
          "ROG Strix X570-E Gaming": {
            "price": 250
          },
          "PRIME B550-PLUS": {
            "price": 150
          },
          "PRIME Z590-A": {
            "price": 180
          }
        }
      },
      "msi": {
        "models": {
          "MSI MPG Z490 Gaming Carbon WiFi": {
            "price": 180
          },
          "MSI MAG B550 Tomahawk": {
            "price": 160
          },
          "MSI MEG Z590 ACE": {
            "price": 220
          },
          "MSI B450 Tomahawk Max": {
            "price": 140
          }
        }
      },
      "gigabyte": {
        "models": {
          "Gigabyte Z590 AORUS Master": {
            "price": 320
          },
          "Gigabyte B550 AORUS Pro AC": {
            "price": 200
          },
          "Gigabyte X570 AORUS Elite": {
            "price": 240
          },
          "Gigabyte B450 AORUS Elite": {
            "price": 140
          }
        }
      }
    }
  },
  "ram": {
    "brands": {
      "corsair": {
        "models": {
          "Corsair Vengeance LPX 16GB": {
            "price": 100
          },
          "Corsair Vengeance RGB Pro 32GB": {
            "price": 180
          },
          "Corsair Vengeance LPX 32GB": {
            "price": 160
          }
        }
      },
      "kingston": {
        "models": {
          "Kingston HyperX Fury 16GB": {
            "price": 90
          },
          "Kingston HyperX Predator RGB 32GB": {
            "price": 160
          },
          "Kingston HyperX Impact 32GB": {
            "price": 140
          }
        }
      },
      "gskill": {
        "models": {
          "G.Skill Ripjaws V 16GB": {
            "price": 110
          },
          "G.Skill Trident Z RGB 32GB": {
            "price": 180
          },
          "G.Skill Ripjaws V 32GB": {
            "price": 160
          }
        }
      }
    }
  },
  "storage": {
    "brands": {
      "samsung": {
        "models": {
          "Samsung 970 EVO Plus 1TB NVMe PCIe M.2 SSD": {
            "price": 200
          },
          "Samsung 870 EVO 500GB SATA III SSD": {
            "price": 100
          },
          "Samsung 860 QVO 2TB SATA III SSD": {
            "price": 250
          }
        }
      },
      "western-digital": {
        "models": {
          "WD Blue SN550 500GB NVMe PCIe M.2 SSD": {
            "price": 80
          },
          "WD Blue 1TB SATA III SSD": {
            "price": 90
          },
          "WD Black SN750 1TB NVMe PCIe M.2 SSD": {
            "price": 180
          }
        }
      },
      "kingston": {
        "models": {
          "Kingston A2000 500GB NVMe PCIe M.2 SSD": {
            "price": 90
          },
          "Kingston KC600 1TB SATA III SSD": {
            "price": 120
          },
          "Kingston UV500 240GB SATA III SSD": {
            "price": 70
          }
        }
      }
    }
  },
  "graphics-card": {
    "brands": {
      "nvidia": {
        "models": {
          "rtx-3060": {
            "price": 400
          },
          "rtx-3070": {
            "price": 500
          },
          "rtx-3080": {
            "price": 700
          }
        }
      },
      "amd": {
        "models": {
          "rx-6700": {
            "price": 450
          },
          "rx-6800": {
            "price": 550
          },
          "rx-6900": {
            "price": 750
          }
        }
      }
    }
  },
  "power-supply": {
    "brands": {
      "corsair": {
        "models": {
          "txm-series": {
            "price": 100
          }
        }
      },
      "evga": {
        "models": {
          "supernova": {
            "price": 110
          }
        }
      },
      "seasonic": {
        "models": {
          "focus-gold": {
            "price": 120
          }
        }
      }
    }
  },
  "case": {
    "brands": {
      "nzxt": {
        "models": {
          "h510": {
            "price": 80
          }
        }
      },
      "corsair": {
        "models": {
          "icue-220t": {
            "price": 90
          }
        }
      },
      "thermaltake": {
        "models": {
          "view-51": {
            "price": 100
          }
        }
      }
    }
  }
}